mcp_server_pak/__init__.py
mcp_server_pak-0.1.0.dist-info/METADATA
mcp_server_pak-0.1.0.dist-info/WHEEL
mcp_server_pak-0.1.0.dist-info/entry_points.txt
mcp_server_pak-0.1.0.dist-info/RECORD
