Metadata-Version: 2.4
Name: mcp-server-pak
Version: 0.1.0
Summary: Add your description here
Author-email: wangfeng <wangfeng@makalu.cc>
Requires-Python: >=3.12
Requires-Dist: mcp[cli]>=1.9.3
